{
  "dates": [
    {
      "date": "2025-06-17",
      "tides": [
        {
          "type": "High",
          "time": "00:21",
          "heightInMetres": 1.9,
          "instant": "2025-06-16T23:21:00Z"
        },
        {
          "type": "Low",
          "time": "09:04",
          "heightInMetres": 0.8,
          "instant": "2025-06-17T08:04:00Z"
        },
        {
          "type": "High",
          "time": "14:13",
          "heightInMetres": 1.8,
          "instant": "2025-06-17T13:13:00Z"
        },
        {
          "type": "Low",
          "time": "21:37",
          "heightInMetres": 1.2,
          "instant": "2025-06-17T20:37:00Z"
        }
      ]
    },
    {
      "date": "2025-06-18",
      "tides": [
        {
          "type": "High",
          "time": "01:00",
          "heightInMetres": 1.9,
          "instant": "2025-06-18T00:00:00Z"
        },
        {
          "type": "Low",
          "time": "09:58",
          "heightInMetres": 0.8,
          "instant": "2025-06-18T08:58:00Z"
        },
        {
          "type": "High",
          "time": "15:08",
          "heightInMetres": 1.7,
          "instant": "2025-06-18T14:08:00Z"
        },
        {
          "type": "Low",
          "time": "22:36",
          "heightInMetres": 1.2,
          "instant": "2025-06-18T21:36:00Z"
        }
      ]
    },
    {
      "date": "2025-06-19",
      "tides": [
        {
          "type": "High",
          "time": "02:44",
          "heightInMetres": 1.8,
          "instant": "2025-06-19T01:44:00Z"
        },
        {
          "type": "Low",
          "time": "10:58",
          "heightInMetres": 0.9,
          "instant": "2025-06-19T09:58:00Z"
        },
        {
          "type": "High",
          "time": "20:15",
          "heightInMetres": 2.0,
          "instant": "2025-06-19T19:15:00Z"
        },
        {
          "type": "Low",
          "time": "23:40",
          "heightInMetres": 1.1,
          "instant": "2025-06-19T22:40:00Z"
        }
      ]
    }
  ]
}