{
  "dates": [
    {
      "date": "2024-04-26",
      "tides": [
        {
          "type": "Low",
          "time": "06:22",
          "height": "0.6m"
        },
        {
          "type": "High",
          "time": "11:16",
          "height": "2.1m"
        },
        {
          "type": "Low",
          "time": "18:36",
          "height": "0.8m"
        },
        {
          "type": "High",
          "time": "23:18",
          "height": "2.1m"
        }
      ]
    },
    {
      "date": "2024-04-27",
      "tides": [
        {
          "type": "Low",
          "time": "06:55",
          "height": "0.7m"
        },
        {
          "type": "High",
          "time": "11:45",
          "height": "2.0m"
        },
        {
          "type": "Low",
          "time": "19:11",
          "height": "0.9m"
        },
        {
          "type": "High",
          "time": "23:23",
          "height": "2.0m"
        }
      ]
    },
    {
      "date": "2024-04-28",
      "tides": [
        {
          "type": "Low",
          "time": "07:31",
          "height": "0.7m"
        },
        {
          "type": "High",
          "time": "11:03",
          "height": "1.9m"
        },
        {
          "type": "Low",
          "time": "19:50",
          "height": "1.0m"
        },
        {
          "type": "High",
          "time": "23:04",
          "height": "2.0m"
        }
      ]
    }
  ]
}