{
  "data": [
    {
      "date": "2024-04-22",
      "hours": [
        {
          "time": "19:00",
          "temperature": "8",
          "chanceOfRain": "77",
          "windSpeedMph": "8",
          "windDirection": "NNW",
          "weatherType": 12,
          "weatherTypeDescription": "Light Rain"
        },
        {
          "time": "20:00",
          "temperature": "8",
          "chanceOfRain": "62",
          "windSpeedMph": "11",
          "windDirection": "N",
          "weatherType": 12,
          "weatherTypeDescription": "Light Rain"
        },
        {
          "time": "21:00",
          "temperature": "8",
          "chanceOfRain": "52",
          "windSpeedMph": "12",
          "windDirection": "NNE",
          "weatherType": 11,
          "weatherTypeDescription": "Drizzle"
        },
        {
          "time": "22:00",
          "temperature": "8",
          "chanceOfRain": "25",
          "windSpeedMph": "11",
          "windDirection": "NNE",
          "weatherType": 8,
          "weatherTypeDescription": "Thick Cloud"
        },
        {
          "time": "23:00",
          "temperature": "7",
          "chanceOfRain": "0",
          "windSpeedMph": "11",
          "windDirection": "NE",
          "weatherType": 7,
          "weatherTypeDescription": "Light Cloud"
        },
        {
          "time": "00:00",
          "temperature": "7",
          "chanceOfRain": "0",
          "windSpeedMph": "11",
          "windDirection": "NE",
          "weatherType": 7,
          "weatherTypeDescription": "Light Cloud"
        },
        {
          "time": "01:00",
          "temperature": "7",
          "chanceOfRain": "0",
          "windSpeedMph": "10",
          "windDirection": "NE",
          "weatherType": 7,
          "weatherTypeDescription": "Light Cloud"
        },
        {
          "time": "02:00",
          "temperature": "7",
          "chanceOfRain": "12",
          "windSpeedMph": "9",
          "windDirection": "NE",
          "weatherType": 7,
          "weatherTypeDescription": "Light Cloud"
        },
        {
          "time": "03:00",
          "temperature": "7",
          "chanceOfRain": "19",
          "windSpeedMph": "9",
          "windDirection": "NNE",
          "weatherType": 7,
          "weatherTypeDescription": "Light Cloud"
        },
        {
          "time": "04:00",
          "temperature": "6",
          "chanceOfRain": "15",
          "windSpeedMph": "9",
          "windDirection": "NNE",
          "weatherType": 7,
          "weatherTypeDescription": "Light Cloud"
        },
        {
          "time": "05:00",
          "temperature": "6",
          "chanceOfRain": "15",
          "windSpeedMph": "9",
          "windDirection": "NNE",
          "weatherType": 7,
          "weatherTypeDescription": "Light Cloud"
        }
      ]
    },
    {
      "date": "2024-04-23",
      "hours": [
        {
          "time": "06:00",
          "temperature": "6",
          "chanceOfRain": "13",
          "windSpeedMph": "9",
          "windDirection": "N",
          "weatherType": 7,
          "weatherTypeDescription": "Light Cloud"
        },
        {
          "time": "07:00",
          "temperature": "6",
          "chanceOfRain": "0",
          "windSpeedMph": "10",
          "windDirection": "N",
          "weatherType": 7,
          "weatherTypeDescription": "Light Cloud"
        },
        {
          "time": "08:00",
          "temperature": "7",
          "chanceOfRain": "0",
          "windSpeedMph": "11",
          "windDirection": "N",
          "weatherType": 7,
          "weatherTypeDescription": "Light Cloud"
        },
        {
          "time": "09:00",
          "temperature": "8",
          "chanceOfRain": "0",
          "windSpeedMph": "13",
          "windDirection": "N",
          "weatherType": 7,
          "weatherTypeDescription": "Light Cloud"
        },
        {
          "time": "10:00",
          "temperature": "9",
          "chanceOfRain": "0",
          "windSpeedMph": "15",
          "windDirection": "N",
          "weatherType": 3,
          "weatherTypeDescription": "Sunny Intervals"
        },
        {
          "time": "11:00",
          "temperature": "10",
          "chanceOfRain": "0",
          "windSpeedMph": "17",
          "windDirection": "N",
          "weatherType": 7,
          "weatherTypeDescription": "Light Cloud"
        },
        {
          "time": "12:00",
          "temperature": "11",
          "chanceOfRain": "0",
          "windSpeedMph": "15",
          "windDirection": "N",
          "weatherType": 7,
          "weatherTypeDescription": "Light Cloud"
        },
        {
          "time": "13:00",
          "temperature": "11",
          "chanceOfRain": "0",
          "windSpeedMph": "17",
          "windDirection": "N",
          "weatherType": 7,
          "weatherTypeDescription": "Light Cloud"
        },
        {
          "time": "14:00",
          "temperature": "11",
          "chanceOfRain": "24",
          "windSpeedMph": "16",
          "windDirection": "N",
          "weatherType": 7,
          "weatherTypeDescription": "Light Cloud"
        },
        {
          "time": "15:00",
          "temperature": "11",
          "chanceOfRain": "24",
          "windSpeedMph": "17",
          "windDirection": "N",
          "weatherType": 7,
          "weatherTypeDescription": "Light Cloud"
        },
        {
          "time": "16:00",
          "temperature": "11",
          "chanceOfRain": "21",
          "windSpeedMph": "18",
          "windDirection": "N",
          "weatherType": 8,
          "weatherTypeDescription": "Thick Cloud"
        },
        {
          "time": "17:00",
          "temperature": "11",
          "chanceOfRain": "15",
          "windSpeedMph": "17",
          "windDirection": "N",
          "weatherType": 7,
          "weatherTypeDescription": "Light Cloud"
        },
        {
          "time": "18:00",
          "temperature": "11",
          "chanceOfRain": "15",
          "windSpeedMph": "13",
          "windDirection": "N",
          "weatherType": 3,
          "weatherTypeDescription": "Sunny Intervals"
        },
        {
          "time": "19:00",
          "temperature": "11",
          "chanceOfRain": "13",
          "windSpeedMph": "13",
          "windDirection": "NNW",
          "weatherType": 3,
          "weatherTypeDescription": "Sunny Intervals"
        },
        {
          "time": "20:00",
          "temperature": "10",
          "chanceOfRain": "0",
          "windSpeedMph": "13",
          "windDirection": "N",
          "weatherType": 3,
          "weatherTypeDescription": "Sunny Intervals"
        },
        {
          "time": "21:00",
          "temperature": "9",
          "chanceOfRain": "0",
          "windSpeedMph": "14",
          "windDirection": "N",
          "weatherType": 2,
          "weatherTypeDescription": "Partly Cloudy"
        },
        {
          "time": "22:00",
          "temperature": "9",
          "chanceOfRain": "0",
          "windSpeedMph": "12",
          "windDirection": "N",
          "weatherType": 2,
          "weatherTypeDescription": "Partly Cloudy"
        },
        {
          "time": "23:00",
          "temperature": "8",
          "chanceOfRain": "0",
          "windSpeedMph": "12",
          "windDirection": "N",
          "weatherType": 2,
          "weatherTypeDescription": "Partly Cloudy"
        },
        {
          "time": "00:00",
          "temperature": "7",
          "chanceOfRain": "0",
          "windSpeedMph": "11",
          "windDirection": "N",
          "weatherType": 2,
          "weatherTypeDescription": "Partly Cloudy"
        },
        {
          "time": "01:00",
          "temperature": "7",
          "chanceOfRain": "0",
          "windSpeedMph": "11",
          "windDirection": "N",
          "weatherType": 2,
          "weatherTypeDescription": "Partly Cloudy"
        },
        {
          "time": "02:00",
          "temperature": "6",
          "chanceOfRain": "0",
          "windSpeedMph": "10",
          "windDirection": "N",
          "weatherType": 2,
          "weatherTypeDescription": "Partly Cloudy"
        },
        {
          "time": "03:00",
          "temperature": "6",
          "chanceOfRain": "0",
          "windSpeedMph": "10",
          "windDirection": "N",
          "weatherType": 2,
          "weatherTypeDescription": "Partly Cloudy"
        },
        {
          "time": "04:00",
          "temperature": "5",
          "chanceOfRain": "0",
          "windSpeedMph": "10",
          "windDirection": "NNW",
          "weatherType": 2,
          "weatherTypeDescription": "Partly Cloudy"
        },
        {
          "time": "05:00",
          "temperature": "5",
          "chanceOfRain": "0",
          "windSpeedMph": "9",
          "windDirection": "N",
          "weatherType": 2,
          "weatherTypeDescription": "Partly Cloudy"
        }
      ]
    },
    {
      "date": "2024-04-24",
      "hours": [
        {
          "time": "06:00",
          "temperature": "5",
          "chanceOfRain": "0",
          "windSpeedMph": "9",
          "windDirection": "NNW",
          "weatherType": 3,
          "weatherTypeDescription": "Sunny Intervals"
        },
        {
          "time": "07:00",
          "temperature": "5",
          "chanceOfRain": "0",
          "windSpeedMph": "10",
          "windDirection": "NNW",
          "weatherType": 3,
          "weatherTypeDescription": "Sunny Intervals"
        },
        {
          "time": "08:00",
          "temperature": "6",
          "chanceOfRain": "0",
          "windSpeedMph": "11",
          "windDirection": "NNW",
          "weatherType": 3,
          "weatherTypeDescription": "Sunny Intervals"
        },
        {
          "time": "09:00",
          "temperature": "7",
          "chanceOfRain": "0",
          "windSpeedMph": "12",
          "windDirection": "NNW",
          "weatherType": 3,
          "weatherTypeDescription": "Sunny Intervals"
        },
        {
          "time": "10:00",
          "temperature": "8",
          "chanceOfRain": "0",
          "windSpeedMph": "12",
          "windDirection": "NNW",
          "weatherType": 3,
          "weatherTypeDescription": "Sunny Intervals"
        },
        {
          "time": "11:00",
          "temperature": "9",
          "chanceOfRain": "0",
          "windSpeedMph": "12",
          "windDirection": "NW",
          "weatherType": 7,
          "weatherTypeDescription": "Light Cloud"
        },
        {
          "time": "12:00",
          "temperature": "10",
          "chanceOfRain": "0",
          "windSpeedMph": "12",
          "windDirection": "NW",
          "weatherType": 7,
          "weatherTypeDescription": "Light Cloud"
        },
        {
          "time": "13:00",
          "temperature": "10",
          "chanceOfRain": "25",
          "windSpeedMph": "12",
          "windDirection": "NW",
          "weatherType": 7,
          "weatherTypeDescription": "Light Cloud"
        },
        {
          "time": "14:00",
          "temperature": "10",
          "chanceOfRain": "54",
          "windSpeedMph": "12",
          "windDirection": "NW",
          "weatherType": 10,
          "weatherTypeDescription": "Light Rain Showers"
        },
        {
          "time": "15:00",
          "temperature": "10",
          "chanceOfRain": "66",
          "windSpeedMph": "12",
          "windDirection": "NW",
          "weatherType": 12,
          "weatherTypeDescription": "Light Rain"
        },
        {
          "time": "16:00",
          "temperature": "11",
          "chanceOfRain": "63",
          "windSpeedMph": "12",
          "windDirection": "NW",
          "weatherType": 12,
          "weatherTypeDescription": "Light Rain"
        },
        {
          "time": "17:00",
          "temperature": "10",
          "chanceOfRain": "46",
          "windSpeedMph": "12",
          "windDirection": "NW",
          "weatherType": 10,
          "weatherTypeDescription": "Light Rain Showers"
        },
        {
          "time": "18:00",
          "temperature": "10",
          "chanceOfRain": "36",
          "windSpeedMph": "12",
          "windDirection": "NW",
          "weatherType": 10,
          "weatherTypeDescription": "Light Rain Showers"
        },
        {
          "time": "19:00",
          "temperature": "10",
          "chanceOfRain": "23",
          "windSpeedMph": "11",
          "windDirection": "NNW",
          "weatherType": 3,
          "weatherTypeDescription": "Sunny Intervals"
        },
        {
          "time": "20:00",
          "temperature": "9",
          "chanceOfRain": "0",
          "windSpeedMph": "11",
          "windDirection": "N",
          "weatherType": 3,
          "weatherTypeDescription": "Sunny Intervals"
        },
        {
          "time": "21:00",
          "temperature": "9",
          "chanceOfRain": "0",
          "windSpeedMph": "11",
          "windDirection": "NNE",
          "weatherType": 2,
          "weatherTypeDescription": "Partly Cloudy"
        },
        {
          "time": "22:00",
          "temperature": "8",
          "chanceOfRain": "0",
          "windSpeedMph": "10",
          "windDirection": "NE",
          "weatherType": 2,
          "weatherTypeDescription": "Partly Cloudy"
        },
        {
          "time": "23:00",
          "temperature": "7",
          "chanceOfRain": "0",
          "windSpeedMph": "10",
          "windDirection": "NE",
          "weatherType": 2,
          "weatherTypeDescription": "Partly Cloudy"
        },
        {
          "time": "00:00",
          "temperature": "7",
          "chanceOfRain": "0",
          "windSpeedMph": "9",
          "windDirection": "NE",
          "weatherType": 2,
          "weatherTypeDescription": "Partly Cloudy"
        },
        {
          "time": "01:00",
          "temperature": "7",
          "chanceOfRain": "0",
          "windSpeedMph": "9",
          "windDirection": "NNE",
          "weatherType": 2,
          "weatherTypeDescription": "Partly Cloudy"
        },
        {
          "time": "02:00",
          "temperature": "6",
          "chanceOfRain": "0",
          "windSpeedMph": "9",
          "windDirection": "NNE",
          "weatherType": 2,
          "weatherTypeDescription": "Partly Cloudy"
        },
        {
          "time": "03:00",
          "temperature": "6",
          "chanceOfRain": "0",
          "windSpeedMph": "10",
          "windDirection": "NNE",
          "weatherType": 2,
          "weatherTypeDescription": "Partly Cloudy"
        },
        {
          "time": "04:00",
          "temperature": "5",
          "chanceOfRain": "0",
          "windSpeedMph": "10",
          "windDirection": "N",
          "weatherType": 2,
          "weatherTypeDescription": "Partly Cloudy"
        },
        {
          "time": "05:00",
          "temperature": "5",
          "chanceOfRain": "0",
          "windSpeedMph": "10",
          "windDirection": "N",
          "weatherType": 2,
          "weatherTypeDescription": "Partly Cloudy"
        }
      ]
    },
    {
      "date": "2024-04-25",
      "hours": [
        {
          "time": "06:00",
          "temperature": "5",
          "chanceOfRain": "0",
          "windSpeedMph": "10",
          "windDirection": "N",
          "weatherType": 1,
          "weatherTypeDescription": "Sunny"
        },
        {
          "time": "07:00",
          "temperature": "5",
          "chanceOfRain": "0",
          "windSpeedMph": "10",
          "windDirection": "N",
          "weatherType": 1,
          "weatherTypeDescription": "Sunny"
        },
        {
          "time": "08:00",
          "temperature": "6",
          "chanceOfRain": "0",
          "windSpeedMph": "10",
          "windDirection": "N",
          "weatherType": 3,
          "weatherTypeDescription": "Sunny Intervals"
        },
        {
          "time": "09:00",
          "temperature": "7",
          "chanceOfRain": "0",
          "windSpeedMph": "10",
          "windDirection": "N",
          "weatherType": 3,
          "weatherTypeDescription": "Sunny Intervals"
        },
        {
          "time": "10:00",
          "temperature": "8",
          "chanceOfRain": "0",
          "windSpeedMph": "10",
          "windDirection": "NNW",
          "weatherType": 3,
          "weatherTypeDescription": "Sunny Intervals"
        },
        {
          "time": "11:00",
          "temperature": "9",
          "chanceOfRain": "0",
          "windSpeedMph": "11",
          "windDirection": "N",
          "weatherType": 3,
          "weatherTypeDescription": "Sunny Intervals"
        },
        {
          "time": "12:00",
          "temperature": "10",
          "chanceOfRain": "9",
          "windSpeedMph": "11",
          "windDirection": "NNW",
          "weatherType": 3,
          "weatherTypeDescription": "Sunny Intervals"
        },
        {
          "time": "13:00",
          "temperature": "10",
          "chanceOfRain": "0",
          "windSpeedMph": "12",
          "windDirection": "WNW",
          "weatherType": 3,
          "weatherTypeDescription": "Sunny Intervals"
        },
        {
          "time": "14:00",
          "temperature": "10",
          "chanceOfRain": "0",
          "windSpeedMph": "13",
          "windDirection": "WSW",
          "weatherType": 3,
          "weatherTypeDescription": "Sunny Intervals"
        },
        {
          "time": "15:00",
          "temperature": "11",
          "chanceOfRain": "11",
          "windSpeedMph": "14",
          "windDirection": "WSW",
          "weatherType": 3,
          "weatherTypeDescription": "Sunny Intervals"
        },
        {
          "time": "16:00",
          "temperature": "11",
          "chanceOfRain": "0",
          "windSpeedMph": "14",
          "windDirection": "SW",
          "weatherType": 3,
          "weatherTypeDescription": "Sunny Intervals"
        },
        {
          "time": "17:00",
          "temperature": "11",
          "chanceOfRain": "22",
          "windSpeedMph": "14",
          "windDirection": "SW",
          "weatherType": 3,
          "weatherTypeDescription": "Sunny Intervals"
        },
        {
          "time": "18:00",
          "temperature": "10",
          "chanceOfRain": "22",
          "windSpeedMph": "14",
          "windDirection": "WSW",
          "weatherType": 3,
          "weatherTypeDescription": "Sunny Intervals"
        },
        {
          "time": "19:00",
          "temperature": "10",
          "chanceOfRain": "21",
          "windSpeedMph": "13",
          "windDirection": "WSW",
          "weatherType": 3,
          "weatherTypeDescription": "Sunny Intervals"
        },
        {
          "time": "20:00",
          "temperature": "9",
          "chanceOfRain": "12",
          "windSpeedMph": "11",
          "windDirection": "WSW",
          "weatherType": 3,
          "weatherTypeDescription": "Sunny Intervals"
        },
        {
          "time": "21:00",
          "temperature": "9",
          "chanceOfRain": "11",
          "windSpeedMph": "10",
          "windDirection": "WSW",
          "weatherType": 2,
          "weatherTypeDescription": "Partly Cloudy"
        },
        {
          "time": "22:00",
          "temperature": "8",
          "chanceOfRain": "13",
          "windSpeedMph": "10",
          "windDirection": "WSW",
          "weatherType": 2,
          "weatherTypeDescription": "Partly Cloudy"
        },
        {
          "time": "23:00",
          "temperature": "8",
          "chanceOfRain": "0",
          "windSpeedMph": "9",
          "windDirection": "WSW",
          "weatherType": 2,
          "weatherTypeDescription": "Partly Cloudy"
        },
        {
          "time": "00:00",
          "temperature": "8",
          "chanceOfRain": "11",
          "windSpeedMph": "9",
          "windDirection": "SW",
          "weatherType": 2,
          "weatherTypeDescription": "Partly Cloudy"
        },
        {
          "time": "01:00",
          "temperature": "7",
          "chanceOfRain": "17",
          "windSpeedMph": "10",
          "windDirection": "WSW",
          "weatherType": 2,
          "weatherTypeDescription": "Partly Cloudy"
        },
        {
          "time": "02:00",
          "temperature": "7",
          "chanceOfRain": "25",
          "windSpeedMph": "10",
          "windDirection": "WSW",
          "weatherType": 9,
          "weatherTypeDescription": "Light Rain Showers"
        },
        {
          "time": "03:00",
          "temperature": "7",
          "chanceOfRain": "20",
          "windSpeedMph": "10",
          "windDirection": "WSW",
          "weatherType": 2,
          "weatherTypeDescription": "Partly Cloudy"
        },
        {
          "time": "04:00",
          "temperature": "7",
          "chanceOfRain": "17",
          "windSpeedMph": "10",
          "windDirection": "SW",
          "weatherType": 2,
          "weatherTypeDescription": "Partly Cloudy"
        },
        {
          "time": "05:00",
          "temperature": "7",
          "chanceOfRain": "0",
          "windSpeedMph": "10",
          "windDirection": "SW",
          "weatherType": 2,
          "weatherTypeDescription": "Partly Cloudy"
        }
      ]
    },
    {
      "date": "2024-04-26",
      "hours": [
        {
          "time": "06:00",
          "temperature": "7",
          "chanceOfRain": "0",
          "windSpeedMph": "10",
          "windDirection": "S",
          "weatherType": 3,
          "weatherTypeDescription": "Sunny Intervals"
        },
        {
          "time": "07:00",
          "temperature": "7",
          "chanceOfRain": "0",
          "windSpeedMph": "11",
          "windDirection": "S",
          "weatherType": 3,
          "weatherTypeDescription": "Sunny Intervals"
        },
        {
          "time": "08:00",
          "temperature": "8",
          "chanceOfRain": "28",
          "windSpeedMph": "12",
          "windDirection": "S",
          "weatherType": 3,
          "weatherTypeDescription": "Sunny Intervals"
        },
        {
          "time": "09:00",
          "temperature": "9",
          "chanceOfRain": "30",
          "windSpeedMph": "14",
          "windDirection": "S",
          "weatherType": 3,
          "weatherTypeDescription": "Sunny Intervals"
        },
        {
          "time": "10:00",
          "temperature": "9",
          "chanceOfRain": "32",
          "windSpeedMph": "14",
          "windDirection": "S",
          "weatherType": 10,
          "weatherTypeDescription": "Light Rain Showers"
        },
        {
          "time": "11:00",
          "temperature": "10",
          "chanceOfRain": "35",
          "windSpeedMph": "15",
          "windDirection": "S",
          "weatherType": 10,
          "weatherTypeDescription": "Light Rain Showers"
        },
        {
          "time": "12:00",
          "temperature": "10",
          "chanceOfRain": "40",
          "windSpeedMph": "16",
          "windDirection": "S",
          "weatherType": 10,
          "weatherTypeDescription": "Light Rain Showers"
        },
        {
          "time": "13:00",
          "temperature": "11",
          "chanceOfRain": "36",
          "windSpeedMph": "16",
          "windDirection": "S",
          "weatherType": 11,
          "weatherTypeDescription": "Drizzle"
        },
        {
          "time": "14:00",
          "temperature": "11",
          "chanceOfRain": "12",
          "windSpeedMph": "15",
          "windDirection": "S",
          "weatherType": 3,
          "weatherTypeDescription": "Sunny Intervals"
        },
        {
          "time": "15:00",
          "temperature": "11",
          "chanceOfRain": "0",
          "windSpeedMph": "14",
          "windDirection": "S",
          "weatherType": 3,
          "weatherTypeDescription": "Sunny Intervals"
        },
        {
          "time": "16:00",
          "temperature": "11",
          "chanceOfRain": "0",
          "windSpeedMph": "14",
          "windDirection": "S",
          "weatherType": 3,
          "weatherTypeDescription": "Sunny Intervals"
        },
        {
          "time": "17:00",
          "temperature": "11",
          "chanceOfRain": "17",
          "windSpeedMph": "14",
          "windDirection": "S",
          "weatherType": 3,
          "weatherTypeDescription": "Sunny Intervals"
        },
        {
          "time": "18:00",
          "temperature": "11",
          "chanceOfRain": "23",
          "windSpeedMph": "14",
          "windDirection": "SSE",
          "weatherType": 3,
          "weatherTypeDescription": "Sunny Intervals"
        },
        {
          "time": "19:00",
          "temperature": "10",
          "chanceOfRain": "14",
          "windSpeedMph": "14",
          "windDirection": "S",
          "weatherType": 3,
          "weatherTypeDescription": "Sunny Intervals"
        },
        {
          "time": "20:00",
          "temperature": "10",
          "chanceOfRain": "27",
          "windSpeedMph": "13",
          "windDirection": "SSE",
          "weatherType": 10,
          "weatherTypeDescription": "Light Rain Showers"
        },
        {
          "time": "21:00",
          "temperature": "9",
          "chanceOfRain": "26",
          "windSpeedMph": "13",
          "windDirection": "SSE",
          "weatherType": 9,
          "weatherTypeDescription": "Light Rain Showers"
        },
        {
          "time": "22:00",
          "temperature": "9",
          "chanceOfRain": "20",
          "windSpeedMph": "13",
          "windDirection": "SSE",
          "weatherType": 12,
          "weatherTypeDescription": "Light Rain"
        },
        {
          "time": "23:00",
          "temperature": "9",
          "chanceOfRain": "22",
          "windSpeedMph": "12",
          "windDirection": "SSE",
          "weatherType": 9,
          "weatherTypeDescription": "Light Rain Showers"
        },
        {
          "time": "00:00",
          "temperature": "9",
          "chanceOfRain": "19",
          "windSpeedMph": "12",
          "windDirection": "SSE",
          "weatherType": 2,
          "weatherTypeDescription": "Partly Cloudy"
        },
        {
          "time": "01:00",
          "temperature": "9",
          "chanceOfRain": "17",
          "windSpeedMph": "14",
          "windDirection": "SSE",
          "weatherType": 0,
          "weatherTypeDescription": "Clear Sky"
        },
        {
          "time": "02:00",
          "temperature": "8",
          "chanceOfRain": "0",
          "windSpeedMph": "15",
          "windDirection": "SSE",
          "weatherType": 0,
          "weatherTypeDescription": "Clear Sky"
        },
        {
          "time": "03:00",
          "temperature": "8",
          "chanceOfRain": "0",
          "windSpeedMph": "16",
          "windDirection": "SE",
          "weatherType": 2,
          "weatherTypeDescription": "Partly Cloudy"
        },
        {
          "time": "04:00",
          "temperature": "8",
          "chanceOfRain": "0",
          "windSpeedMph": "17",
          "windDirection": "SE",
          "weatherType": 2,
          "weatherTypeDescription": "Partly Cloudy"
        },
        {
          "time": "05:00",
          "temperature": "8",
          "chanceOfRain": "8",
          "windSpeedMph": "19",
          "windDirection": "SE",
          "weatherType": 2,
          "weatherTypeDescription": "Partly Cloudy"
        }
      ]
    }
  ]
}